pyenvjasmine/__init__.py
pyenvjasmine/run-jasmine3.js
pyenvjasmine/runner.html
pyenvjasmine/runner.py
pyenvjasmine/runner3.html
pyenvjasmine/envjasmine/.gitignore
pyenvjasmine/envjasmine/.travis.yml
pyenvjasmine/envjasmine/CHANGELOG
pyenvjasmine/envjasmine/EnvJasmine.gemspec
pyenvjasmine/envjasmine/LICENSE
pyenvjasmine/envjasmine/README.textile
pyenvjasmine/envjasmine/VERSION
pyenvjasmine/envjasmine/sonar-project.properties
pyenvjasmine/envjasmine/sonar.js.xml
pyenvjasmine/envjasmine/bin/envjs_run_coverage
pyenvjasmine/envjasmine/bin/envjs_run_test
pyenvjasmine/envjasmine/bin/run_all_tests.bat
pyenvjasmine/envjasmine/bin/run_all_tests.sh
pyenvjasmine/envjasmine/bin/run_coverage.sh
pyenvjasmine/envjasmine/bin/run_test.bat
pyenvjasmine/envjasmine/bin/run_test.sh
pyenvjasmine/envjasmine/include/dependencies.js
pyenvjasmine/envjasmine/include/jquery-1.4.4.js
pyenvjasmine/envjasmine/lib/envjasmine.html
pyenvjasmine/envjasmine/lib/envjasmine.js
pyenvjasmine/envjasmine/lib/envjs/env.rhino.1.2.js
pyenvjasmine/envjasmine/lib/jasmine/MIT.LICENSE
pyenvjasmine/envjasmine/lib/jasmine/jasmine-html.js
pyenvjasmine/envjasmine/lib/jasmine/jasmine.css
pyenvjasmine/envjasmine/lib/jasmine/jasmine.js
pyenvjasmine/envjasmine/lib/jasmine/jasmine_favicon.png
pyenvjasmine/envjasmine/lib/jasmine-3.1.0/boot.js
pyenvjasmine/envjasmine/lib/jasmine-3.1.0/jasmine-html.js
pyenvjasmine/envjasmine/lib/jasmine-3.1.0/jasmine.css
pyenvjasmine/envjasmine/lib/jasmine-3.1.0/jasmine.js
pyenvjasmine/envjasmine/lib/jasmine-ajax/mock-ajax.js
pyenvjasmine/envjasmine/lib/jasmine-ajax/spec-helper.js
pyenvjasmine/envjasmine/lib/jasmine-jquery/jasmine-jquery-1.2.0.js
pyenvjasmine/envjasmine/lib/jasmine-jquery/jasmine-jquery-master.js
pyenvjasmine/envjasmine/lib/jasmine-jquery/jasmine-jquery.js
pyenvjasmine/envjasmine/lib/jasmine-jquery/jasmine3-jquery.js
pyenvjasmine/envjasmine/lib/jasmine-rhino-reporter/jasmine-rhino-reporter.js
pyenvjasmine/envjasmine/lib/jscover/JSCover-all.jar
pyenvjasmine-0.3.1.dist-info/AUTHORS
pyenvjasmine-0.3.1.dist-info/LICENSE
pyenvjasmine-0.3.1.dist-info/METADATA
pyenvjasmine-0.3.1.dist-info/WHEEL
pyenvjasmine-0.3.1.dist-info/top_level.txt
pyenvjasmine-0.3.1.dist-info/RECORD
