Metadata-Version: 2.1
Name: pyenvjasmine
Version: 0.3.1
Summary: A Python wrapper for envjasmine
Home-page: https://code.codigo23.net/trac/wiki/pyenvjasmine
Author: Sascha Welter
Author-email: sw@betabug-sirius.ch
Maintainer: Francisco de Borja Lopez Rio
Maintainer-email: borja@codigo23.net
License: BSD licence, see LICENSE
Download-URL: http://pypi.python.org/pypi/pyenvjasmine#downloads
Platform: UNKNOWN
Classifier: Development Status :: 5 - Production/Stable
Classifier: Environment :: Console
Classifier: Intended Audience :: Developers
Classifier: License :: OSI Approved :: BSD License
Classifier: Natural Language :: English
Classifier: Operating System :: OS Independent
Classifier: Programming Language :: Python :: 2
Classifier: Programming Language :: Python :: 3
Classifier: Programming Language :: JavaScript
Classifier: Topic :: Software Development
Classifier: Topic :: Software Development :: Testing
Requires-Dist: coverage
Requires-Dist: pyflakes
Requires-Dist: pytest
Requires-Dist: pytest-cov
Requires-Dist: pytest-flakes
